README.md
setup.py
mtexplore/__init__.py
mtexplore/mt_main.py
mtexplore.egg-info/PKG-INFO
mtexplore.egg-info/SOURCES.txt
mtexplore.egg-info/dependency_links.txt
mtexplore.egg-info/requires.txt
mtexplore.egg-info/top_level.txt
mtexplore/controller/__init__.py
mtexplore/controller/controller.py
mtexplore/controller/controller_abstracts.py
mtexplore/controller/cycle_controller.py
mtexplore/controller/map_controller.py
mtexplore/controller/save_controller.py
mtexplore/controller/scroll_controller.py
mtexplore/controller/selection_controller.py
mtexplore/model/__init__.py
mtexplore/model/database_model.py
mtexplore/model/modelcontroller.py
mtexplore/model/mt_py_facade.py
mtexplore/view/__init__.py
mtexplore/view/map_view.py
mtexplore/view/mt_view.py
mtexplore/view/view.py
mtexplore/view/view_base.py