Metadata-Version: 2.1
Name: mtexplore
Version: 0.0.6
Summary: MT Explore is a cartopy and mtpy based utility for viewing and cleaning Magnetotelluric data
Home-page: https://github.com/El-minadero/mt-explore
Author: Kevin Mendoza
Author-email: kevinmendoza@icloud.com
License: UNKNOWN
Platform: UNKNOWN
Classifier: Programming Language :: Python :: 3.6
Classifier: License :: OSI Approved :: GNU General Public License v3 (GPLv3)
Classifier: Operating System :: OS Independent
